syp/__init__.py
syp/settings.py
syp/syp.py
syp/test_syp.py
syp-0.1.7.data/scripts/README.org
syp-0.1.7.data/scripts/settings.py
syp-0.1.7.data/scripts/syp.py
syp-0.1.7.dist-info/DESCRIPTION.rst
syp-0.1.7.dist-info/METADATA
syp-0.1.7.dist-info/RECORD
syp-0.1.7.dist-info/WHEEL
syp-0.1.7.dist-info/entry_points.txt
syp-0.1.7.dist-info/metadata.json
syp-0.1.7.dist-info/top_level.txt
