Metadata-Version: 2.0
Name: syp
Version: 0.1.7
Summary: Sync your packages with your dotfiles (and vice versa).
Home-page: https://github.com/vindarel/syp
Author: vindarel
Author-email: ehvince@mailz.org
License: GNU GPLv3
Keywords: utility packages shell
Platform: UNKNOWN
Classifier: Environment :: Console
Classifier: License :: Public Domain
Classifier: Topic :: Utilities
Requires-Dist: addict
Requires-Dist: clize
Requires-Dist: future
Requires-Dist: six
Requires-Dist: termcolor
